mylibrary/__init__.py
mylibrary/square_num.py
square_trial-0.0.1.dist-info/METADATA
square_trial-0.0.1.dist-info/WHEEL
square_trial-0.0.1.dist-info/top_level.txt
square_trial-0.0.1.dist-info/RECORD
