Metadata-Version: 2.1
Name: square-trial
Version: 0.0.1
Summary: Square number libary trial
Author: Movin Fernandes
Author-email: movin.fernandes@hotmail.com
Keywords: square,number,trial,test
